<?xml version="1.0" encoding="UTF-8"?>
<objects serializationModel="Studio.02.03.00">
	<object class="Event" id="{71652be2-6954-4229-b37a-e1d7e7e53fe2}">
		<property name="color">
			<value>Green</value>
		</property>
		<property name="name">
			<value>ConveyorBelt_OnPush</value>
		</property>
		<property name="outputFormat">
			<value>1</value>
		</property>
		<relationship name="folder">
			<destination>{28e560c1-1a45-4d41-bf13-663b405b98ab}</destination>
		</relationship>
		<relationship name="mixer">
			<destination>{23534267-d544-4f51-84a6-93cef421d0b2}</destination>
		</relationship>
		<relationship name="masterTrack">
			<destination>{7f679d48-266d-4529-986c-b32fd01ac6ee}</destination>
		</relationship>
		<relationship name="mixerInput">
			<destination>{5fdacd2a-a98c-401f-94fe-73f6fc90ff7d}</destination>
		</relationship>
		<relationship name="automatableProperties">
			<destination>{6ca02ced-0851-4d08-ade3-bbe2bca28c6e}</destination>
		</relationship>
		<relationship name="markerTracks">
			<destination>{8218f45e-2a82-4479-8458-b0f2959353ea}</destination>
		</relationship>
		<relationship name="groupTracks">
			<destination>{a2b13cc2-2aaa-4ede-a6a4-a44d2cbfe81b}</destination>
		</relationship>
		<relationship name="timeline">
			<destination>{e5773213-9db2-4841-9023-a40734f084df}</destination>
		</relationship>
		<relationship name="banks">
			<destination>{679ba963-a3f7-4487-9093-dcd85e366d73}</destination>
		</relationship>
	</object>
	<object class="EventMixer" id="{23534267-d544-4f51-84a6-93cef421d0b2}">
		<relationship name="masterBus">
			<destination>{ea9646c2-8fcc-44f4-b755-012b22f91e57}</destination>
		</relationship>
	</object>
	<object class="MasterTrack" id="{7f679d48-266d-4529-986c-b32fd01ac6ee}">
		<relationship name="mixerGroup">
			<destination>{ea9646c2-8fcc-44f4-b755-012b22f91e57}</destination>
		</relationship>
	</object>
	<object class="MixerInput" id="{5fdacd2a-a98c-401f-94fe-73f6fc90ff7d}">
		<relationship name="effectChain">
			<destination>{d08dbabe-a9b1-4e26-aa95-441e4e79a8bc}</destination>
		</relationship>
		<relationship name="panner">
			<destination>{a3e876a5-2269-42a8-b6a1-c6ae51a118ce}</destination>
		</relationship>
		<relationship name="output">
			<destination>{78beedb9-4b69-4d21-a1ed-ff0442fe30fa}</destination>
		</relationship>
	</object>
	<object class="EventAutomatableProperties" id="{6ca02ced-0851-4d08-ade3-bbe2bca28c6e}">
		<property name="maxVoices">
			<value>1</value>
		</property>
	</object>
	<object class="MarkerTrack" id="{8218f45e-2a82-4479-8458-b0f2959353ea}" />
	<object class="GroupTrack" id="{a2b13cc2-2aaa-4ede-a6a4-a44d2cbfe81b}">
		<relationship name="modules">
			<destination>{30fd1ea3-1b2c-498c-a39c-a3a03c928b35}</destination>
		</relationship>
		<relationship name="mixerGroup">
			<destination>{7afb6388-6988-40a2-980b-3b2fdbc60668}</destination>
		</relationship>
	</object>
	<object class="Timeline" id="{e5773213-9db2-4841-9023-a40734f084df}">
		<relationship name="modules">
			<destination>{30fd1ea3-1b2c-498c-a39c-a3a03c928b35}</destination>
		</relationship>
	</object>
	<object class="EventMixerMaster" id="{ea9646c2-8fcc-44f4-b755-012b22f91e57}">
		<relationship name="effectChain">
			<destination>{ebe1478b-28a7-4744-b45f-5e639ae64c8a}</destination>
		</relationship>
		<relationship name="panner">
			<destination>{b27075a6-11a3-4c9b-bc24-131b296a7830}</destination>
		</relationship>
		<relationship name="mixer">
			<destination>{23534267-d544-4f51-84a6-93cef421d0b2}</destination>
		</relationship>
	</object>
	<object class="MixerBusEffectChain" id="{d08dbabe-a9b1-4e26-aa95-441e4e79a8bc}">
		<relationship name="effects">
			<destination>{d767ed40-bf30-4628-99dd-e34ea4949414}</destination>
		</relationship>
	</object>
	<object class="MixerBusPanner" id="{a3e876a5-2269-42a8-b6a1-c6ae51a118ce}" />
	<object class="SingleSound" id="{30fd1ea3-1b2c-498c-a39c-a3a03c928b35}">
		<property name="start">
			<value>0.10000000000000001</value>
		</property>
		<property name="length">
			<value>0.54546485260770972</value>
		</property>
		<property name="volume">
			<value>-4</value>
		</property>
		<relationship name="audioFile">
			<destination>{7438c04e-68b6-40c0-ac76-7dc2eae2b2a4}</destination>
		</relationship>
	</object>
	<object class="EventMixerGroup" id="{7afb6388-6988-40a2-980b-3b2fdbc60668}">
		<property name="name">
			<value>Audio 1</value>
		</property>
		<relationship name="effectChain">
			<destination>{41763e7c-230a-4884-b139-38dcaae0a99d}</destination>
		</relationship>
		<relationship name="panner">
			<destination>{30bdc07b-e5a0-423c-82b1-2a7becba3486}</destination>
		</relationship>
		<relationship name="output">
			<destination>{ea9646c2-8fcc-44f4-b755-012b22f91e57}</destination>
		</relationship>
	</object>
	<object class="MixerBusEffectChain" id="{ebe1478b-28a7-4744-b45f-5e639ae64c8a}">
		<relationship name="effects">
			<destination>{f800956e-5bbd-4990-948c-ecbcdc0a5244}</destination>
		</relationship>
	</object>
	<object class="MixerBusPanner" id="{b27075a6-11a3-4c9b-bc24-131b296a7830}" />
	<object class="MixerBusFader" id="{d767ed40-bf30-4628-99dd-e34ea4949414}" />
	<object class="MixerBusEffectChain" id="{41763e7c-230a-4884-b139-38dcaae0a99d}">
		<relationship name="effects">
			<destination>{56ea11a8-6973-42c4-8e9f-251ba7538db1}</destination>
			<destination>{82fb0636-46ca-45d3-ab66-256a944bd465}</destination>
		</relationship>
	</object>
	<object class="MixerBusPanner" id="{30bdc07b-e5a0-423c-82b1-2a7becba3486}" />
	<object class="MixerBusFader" id="{f800956e-5bbd-4990-948c-ecbcdc0a5244}" />
	<object class="MixerBusFader" id="{56ea11a8-6973-42c4-8e9f-251ba7538db1}" />
	<object class="ThreeEQEffect" id="{82fb0636-46ca-45d3-ab66-256a944bd465}">
		<property name="lowGain">
			<value>-10.5</value>
		</property>
		<property name="highGain">
			<value>-10</value>
		</property>
	</object>
</objects>
